{
    "/js/app.js": "/js/app.js",
    "/js/app.a6b01e26f5b83d0410d9.hot-update.js": "/js/app.a6b01e26f5b83d0410d9.hot-update.js",
    "/js/app.748fcc3938b5d49e211b.hot-update.js": "/js/app.748fcc3938b5d49e211b.hot-update.js",
    "/js/app.e9cdefbfcf12a885c9ca.hot-update.js": "/js/app.e9cdefbfcf12a885c9ca.hot-update.js",
    "/js/app.3c4b870de18ab22f7b4e.hot-update.js": "/js/app.3c4b870de18ab22f7b4e.hot-update.js",
    "/js/app.3f473715fbab8ae3db66.hot-update.js": "/js/app.3f473715fbab8ae3db66.hot-update.js",
    "/js/app.7e564921b1e91e1b51e5.hot-update.js": "/js/app.7e564921b1e91e1b51e5.hot-update.js",
    "/js/app.8a367663499e41db4443.hot-update.js": "/js/app.8a367663499e41db4443.hot-update.js",
    "/js/app.53b1281542abf8a3613c.hot-update.js": "/js/app.53b1281542abf8a3613c.hot-update.js",
    "/js/app.cee6f4cee16e7a8b1fe0.hot-update.js": "/js/app.cee6f4cee16e7a8b1fe0.hot-update.js",
    "/js/app.24bdba5126e64fbffe7d.hot-update.js": "/js/app.24bdba5126e64fbffe7d.hot-update.js",
    "/js/app.dff36ad9115dd30f8aea.hot-update.js": "/js/app.dff36ad9115dd30f8aea.hot-update.js",
    "/js/app.4fd14e77bb4b54d0d9a2.hot-update.js": "/js/app.4fd14e77bb4b54d0d9a2.hot-update.js",
    "/js/app.59dbc73d1a36317ad219.hot-update.js": "/js/app.59dbc73d1a36317ad219.hot-update.js",
    "/js/app.f3ce3b74019d987762f8.hot-update.js": "/js/app.f3ce3b74019d987762f8.hot-update.js",
    "/js/app.5af21baaa026e9ae17b4.hot-update.js": "/js/app.5af21baaa026e9ae17b4.hot-update.js",
    "/js/app.c1baf8dd4ad393fd6808.hot-update.js": "/js/app.c1baf8dd4ad393fd6808.hot-update.js",
    "/js/app.8f648889d3b9e63211cf.hot-update.js": "/js/app.8f648889d3b9e63211cf.hot-update.js",
    "/js/app.87c5e08fd79eb22bf3fa.hot-update.js": "/js/app.87c5e08fd79eb22bf3fa.hot-update.js",
    "/js/app.3094e8ed9a974bd16525.hot-update.js": "/js/app.3094e8ed9a974bd16525.hot-update.js",
    "/js/app.fade8a461452281adefd.hot-update.js": "/js/app.fade8a461452281adefd.hot-update.js",
    "/js/app.3d660e10ac85902e11f4.hot-update.js": "/js/app.3d660e10ac85902e11f4.hot-update.js",
    "/js/app.dc4decc8505c1a112a3b.hot-update.js": "/js/app.dc4decc8505c1a112a3b.hot-update.js",
    "/js/app.7b16d7162e33e195fca3.hot-update.js": "/js/app.7b16d7162e33e195fca3.hot-update.js",
    "/js/app.183a03894ffd13f07ebe.hot-update.js": "/js/app.183a03894ffd13f07ebe.hot-update.js",
    "/js/app.604920b58b96bd907ac6.hot-update.js": "/js/app.604920b58b96bd907ac6.hot-update.js",
    "/js/app.31a6e84bb937b89ad485.hot-update.js": "/js/app.31a6e84bb937b89ad485.hot-update.js",
    "/js/app.a5864d5c489dcbdbe6b3.hot-update.js": "/js/app.a5864d5c489dcbdbe6b3.hot-update.js",
    "/js/app.718c308f208fd44fee30.hot-update.js": "/js/app.718c308f208fd44fee30.hot-update.js",
    "/js/app.6759bce019b8356e3c4a.hot-update.js": "/js/app.6759bce019b8356e3c4a.hot-update.js",
    "/js/app.12f71483e40bba279fc1.hot-update.js": "/js/app.12f71483e40bba279fc1.hot-update.js",
    "/js/app.746ea79be7dbd82fb4eb.hot-update.js": "/js/app.746ea79be7dbd82fb4eb.hot-update.js",
    "/js/app.e7e2b0e0fd5bd5e0f098.hot-update.js": "/js/app.e7e2b0e0fd5bd5e0f098.hot-update.js",
    "/js/app.5be3ee52d4f067d9ae58.hot-update.js": "/js/app.5be3ee52d4f067d9ae58.hot-update.js",
    "/js/app.82ee994ac079f56489de.hot-update.js": "/js/app.82ee994ac079f56489de.hot-update.js",
    "/js/app.b496d6e7c6a39b236fdc.hot-update.js": "/js/app.b496d6e7c6a39b236fdc.hot-update.js",
    "/js/app.9b5355d17cc0cb8b2459.hot-update.js": "/js/app.9b5355d17cc0cb8b2459.hot-update.js",
    "/js/app.7f47e37be9133b19f9d1.hot-update.js": "/js/app.7f47e37be9133b19f9d1.hot-update.js",
    "/js/app.b1a71acac3285d54625c.hot-update.js": "/js/app.b1a71acac3285d54625c.hot-update.js",
    "/js/app.74fc36a3909c3fa5ddd7.hot-update.js": "/js/app.74fc36a3909c3fa5ddd7.hot-update.js",
    "/js/app.3f1a23d1a57baf5729b5.hot-update.js": "/js/app.3f1a23d1a57baf5729b5.hot-update.js",
    "/js/app.4fa2d46e9ac720bdeadb.hot-update.js": "/js/app.4fa2d46e9ac720bdeadb.hot-update.js",
    "/js/app.1b4c5392fa3974f06ff0.hot-update.js": "/js/app.1b4c5392fa3974f06ff0.hot-update.js",
    "/js/app.279537ca92a76215643f.hot-update.js": "/js/app.279537ca92a76215643f.hot-update.js",
    "/js/app.282b8f469d8779cebbd8.hot-update.js": "/js/app.282b8f469d8779cebbd8.hot-update.js",
    "/js/app.4eeefbe3cf224bdd59b1.hot-update.js": "/js/app.4eeefbe3cf224bdd59b1.hot-update.js",
    "/js/app.450383a22bdbd033b70a.hot-update.js": "/js/app.450383a22bdbd033b70a.hot-update.js",
    "/js/app.e287e5d8bd13911e2c63.hot-update.js": "/js/app.e287e5d8bd13911e2c63.hot-update.js",
    "/js/app.d83722bd7f7dd64a7e18.hot-update.js": "/js/app.d83722bd7f7dd64a7e18.hot-update.js",
    "/js/app.8baa9a8063ceb710ba35.hot-update.js": "/js/app.8baa9a8063ceb710ba35.hot-update.js",
    "/js/app.262988974b012d321bda.hot-update.js": "/js/app.262988974b012d321bda.hot-update.js",
    "/js/app.947eb2ffddb24c0865aa.hot-update.js": "/js/app.947eb2ffddb24c0865aa.hot-update.js",
    "/js/app.3d4ad62bd25a024f4a3c.hot-update.js": "/js/app.3d4ad62bd25a024f4a3c.hot-update.js",
    "/js/app.cd20f794f88086a47c22.hot-update.js": "/js/app.cd20f794f88086a47c22.hot-update.js",
    "/js/app.6da54bee51e8c3843489.hot-update.js": "/js/app.6da54bee51e8c3843489.hot-update.js",
    "/js/app.12b3c1307eaa28713637.hot-update.js": "/js/app.12b3c1307eaa28713637.hot-update.js",
    "/js/app.a7762d8669966a62d3fc.hot-update.js": "/js/app.a7762d8669966a62d3fc.hot-update.js",
    "/js/app.5490ad06aa4fbc9741ca.hot-update.js": "/js/app.5490ad06aa4fbc9741ca.hot-update.js",
    "/js/app.9a298d4fbb69b1be012f.hot-update.js": "/js/app.9a298d4fbb69b1be012f.hot-update.js",
    "/js/app.16d43145619f0dc1edd8.hot-update.js": "/js/app.16d43145619f0dc1edd8.hot-update.js",
    "/js/app.be5b9c26491226273e7a.hot-update.js": "/js/app.be5b9c26491226273e7a.hot-update.js",
    "/js/app.b9c6bcb8705ba8a46e62.hot-update.js": "/js/app.b9c6bcb8705ba8a46e62.hot-update.js",
    "/js/app.429388b0d271997babc9.hot-update.js": "/js/app.429388b0d271997babc9.hot-update.js",
    "/js/app.63c67a2288b6553edb50.hot-update.js": "/js/app.63c67a2288b6553edb50.hot-update.js",
    "/js/app.a844f5d8d84573a990f7.hot-update.js": "/js/app.a844f5d8d84573a990f7.hot-update.js",
    "/js/app.e22ec58a32e901cc96a4.hot-update.js": "/js/app.e22ec58a32e901cc96a4.hot-update.js",
    "/js/app.c5402b84fac9484d2a59.hot-update.js": "/js/app.c5402b84fac9484d2a59.hot-update.js",
    "/js/app.52b4b5bc4edee22e2b92.hot-update.js": "/js/app.52b4b5bc4edee22e2b92.hot-update.js",
    "/js/app.13ade7558bb644659d2c.hot-update.js": "/js/app.13ade7558bb644659d2c.hot-update.js",
    "/js/app.ac27502d4bba2b507e35.hot-update.js": "/js/app.ac27502d4bba2b507e35.hot-update.js",
    "/js/app.4c60856448d7e6926065.hot-update.js": "/js/app.4c60856448d7e6926065.hot-update.js",
    "/js/app.9f3cad63f148492e0be0.hot-update.js": "/js/app.9f3cad63f148492e0be0.hot-update.js",
    "/js/app.6349117fe0edcf068c25.hot-update.js": "/js/app.6349117fe0edcf068c25.hot-update.js",
    "/js/app.42ff59fcfc8dcbeed49f.hot-update.js": "/js/app.42ff59fcfc8dcbeed49f.hot-update.js",
    "/js/app.d2a931bb98484d8195b3.hot-update.js": "/js/app.d2a931bb98484d8195b3.hot-update.js",
    "/js/app.ac01dae074392bb3cfd6.hot-update.js": "/js/app.ac01dae074392bb3cfd6.hot-update.js",
    "/js/app.2bbba2de70ead5317c7e.hot-update.js": "/js/app.2bbba2de70ead5317c7e.hot-update.js",
    "/js/app.6301da40dd2dddea6527.hot-update.js": "/js/app.6301da40dd2dddea6527.hot-update.js",
    "/js/app.da5cb7f392a8c20428e2.hot-update.js": "/js/app.da5cb7f392a8c20428e2.hot-update.js",
    "/js/app.74ed8db3c69cc9ffecb4.hot-update.js": "/js/app.74ed8db3c69cc9ffecb4.hot-update.js",
    "/js/app.0c736304213331656e03.hot-update.js": "/js/app.0c736304213331656e03.hot-update.js",
    "/js/app.e0a20ce78b8e41a6635d.hot-update.js": "/js/app.e0a20ce78b8e41a6635d.hot-update.js",
    "/js/app.03e3e1317cf4dc5f44c0.hot-update.js": "/js/app.03e3e1317cf4dc5f44c0.hot-update.js",
    "/js/app.93226a56a201b2678dd2.hot-update.js": "/js/app.93226a56a201b2678dd2.hot-update.js",
    "/js/app.1a6c1d266d76c27fccdf.hot-update.js": "/js/app.1a6c1d266d76c27fccdf.hot-update.js",
    "/js/app.2984f2e11d181cc8b77f.hot-update.js": "/js/app.2984f2e11d181cc8b77f.hot-update.js",
    "/js/app.2014f955705151e93ac4.hot-update.js": "/js/app.2014f955705151e93ac4.hot-update.js",
    "/js/app.23e496b8f994cac2766c.hot-update.js": "/js/app.23e496b8f994cac2766c.hot-update.js",
    "/js/app.21b99de74de3a7e933d6.hot-update.js": "/js/app.21b99de74de3a7e933d6.hot-update.js",
    "/js/app.3e43a16f218d51b688b6.hot-update.js": "/js/app.3e43a16f218d51b688b6.hot-update.js",
    "/js/app.d3658b859d65fb2128e1.hot-update.js": "/js/app.d3658b859d65fb2128e1.hot-update.js",
    "/js/app.6d700cea74cdd24cc7fc.hot-update.js": "/js/app.6d700cea74cdd24cc7fc.hot-update.js",
    "/js/app.47f4616937b967c75d03.hot-update.js": "/js/app.47f4616937b967c75d03.hot-update.js",
    "/js/app.11f3fd0e6c2c090c5bd2.hot-update.js": "/js/app.11f3fd0e6c2c090c5bd2.hot-update.js",
    "/js/app.53431e40c3cb158d0b93.hot-update.js": "/js/app.53431e40c3cb158d0b93.hot-update.js",
    "/js/app.fde1b5396a7a9ab24764.hot-update.js": "/js/app.fde1b5396a7a9ab24764.hot-update.js",
    "/js/app.f5ab5538fc8ab9c781a9.hot-update.js": "/js/app.f5ab5538fc8ab9c781a9.hot-update.js",
    "/js/app.866c16cd90a42095df93.hot-update.js": "/js/app.866c16cd90a42095df93.hot-update.js",
    "/js/app.9e341ce0ba2c4393a08d.hot-update.js": "/js/app.9e341ce0ba2c4393a08d.hot-update.js",
    "/js/app.f1226e0dc0d576242d8e.hot-update.js": "/js/app.f1226e0dc0d576242d8e.hot-update.js",
    "/js/app.650773d5ebf76b4ddd0c.hot-update.js": "/js/app.650773d5ebf76b4ddd0c.hot-update.js",
    "/js/app.21c8433acae7a87a5320.hot-update.js": "/js/app.21c8433acae7a87a5320.hot-update.js",
    "/js/app.ca24157234de17e43a11.hot-update.js": "/js/app.ca24157234de17e43a11.hot-update.js",
    "/js/app.70afc3cb6f5df187d8e7.hot-update.js": "/js/app.70afc3cb6f5df187d8e7.hot-update.js",
    "/js/app.bc2b0fc8a8a2e0f24231.hot-update.js": "/js/app.bc2b0fc8a8a2e0f24231.hot-update.js",
    "/js/app.889d393f78f3763561df.hot-update.js": "/js/app.889d393f78f3763561df.hot-update.js",
    "/js/app.583ee7a34a3161cc6009.hot-update.js": "/js/app.583ee7a34a3161cc6009.hot-update.js",
    "/js/app.21aa2b12b3d4fdaf12db.hot-update.js": "/js/app.21aa2b12b3d4fdaf12db.hot-update.js",
    "/js/app.76123cc10688b7db69cc.hot-update.js": "/js/app.76123cc10688b7db69cc.hot-update.js",
    "/js/app.a00dcee93683e55ed354.hot-update.js": "/js/app.a00dcee93683e55ed354.hot-update.js",
    "/js/app.b354473e76dee52d4fcc.hot-update.js": "/js/app.b354473e76dee52d4fcc.hot-update.js",
    "/js/app.222f44a77f2af9f82377.hot-update.js": "/js/app.222f44a77f2af9f82377.hot-update.js",
    "/js/app.09a51b630ea37db288a6.hot-update.js": "/js/app.09a51b630ea37db288a6.hot-update.js",
    "/js/app.8cdec5635285b45acec5.hot-update.js": "/js/app.8cdec5635285b45acec5.hot-update.js",
    "/js/app.4d183139ef471d318881.hot-update.js": "/js/app.4d183139ef471d318881.hot-update.js",
    "/js/app.c1887e205375b173d3b3.hot-update.js": "/js/app.c1887e205375b173d3b3.hot-update.js",
    "/js/app.df6cda405b4a4b1458f2.hot-update.js": "/js/app.df6cda405b4a4b1458f2.hot-update.js",
    "/js/app.31ce70e9cac7b12e5f63.hot-update.js": "/js/app.31ce70e9cac7b12e5f63.hot-update.js",
    "/js/app.7e63b8f4ddc508ae83ee.hot-update.js": "/js/app.7e63b8f4ddc508ae83ee.hot-update.js",
    "/js/app.e486c1a9af7a661865b3.hot-update.js": "/js/app.e486c1a9af7a661865b3.hot-update.js",
    "/js/app.23e350761fc10aaaf0a5.hot-update.js": "/js/app.23e350761fc10aaaf0a5.hot-update.js",
    "/js/app.6c15a03bd2f51d896781.hot-update.js": "/js/app.6c15a03bd2f51d896781.hot-update.js",
    "/js/app.8a5670f8a438de6b952a.hot-update.js": "/js/app.8a5670f8a438de6b952a.hot-update.js",
    "/js/app.861a352d95f5c57a8c2b.hot-update.js": "/js/app.861a352d95f5c57a8c2b.hot-update.js",
    "/js/app.80d8086dae844db6291e.hot-update.js": "/js/app.80d8086dae844db6291e.hot-update.js",
    "/js/app.7a60b8533c6d8757ab63.hot-update.js": "/js/app.7a60b8533c6d8757ab63.hot-update.js",
    "/js/app.867bffc8fb6fffaddec8.hot-update.js": "/js/app.867bffc8fb6fffaddec8.hot-update.js",
    "/js/app.9ebc84d4539e4d1d160e.hot-update.js": "/js/app.9ebc84d4539e4d1d160e.hot-update.js",
    "/js/app.695a5c1674f73079f0b4.hot-update.js": "/js/app.695a5c1674f73079f0b4.hot-update.js",
    "/js/app.5a5a17ea9dd5837205ae.hot-update.js": "/js/app.5a5a17ea9dd5837205ae.hot-update.js",
    "/js/app.b107c2c97e68a5476e40.hot-update.js": "/js/app.b107c2c97e68a5476e40.hot-update.js",
    "/js/app.696ceb6dc95b5fa1f6ea.hot-update.js": "/js/app.696ceb6dc95b5fa1f6ea.hot-update.js",
    "/js/app.2b7f8b74e7e1d2420a6b.hot-update.js": "/js/app.2b7f8b74e7e1d2420a6b.hot-update.js",
    "/js/app.e11329073cb5bbc545ef.hot-update.js": "/js/app.e11329073cb5bbc545ef.hot-update.js",
    "/js/app.b14a498c3b3bc672e589.hot-update.js": "/js/app.b14a498c3b3bc672e589.hot-update.js"
}
