{
    "/js/app.js": "/js/app.js",
    "/js/app.9e20501242277326c9ec.hot-update.js": "/js/app.9e20501242277326c9ec.hot-update.js",
    "/js/app.aefb8e129dd6a0108b91.hot-update.js": "/js/app.aefb8e129dd6a0108b91.hot-update.js",
    "/js/app.7290745b9112868a8cd5.hot-update.js": "/js/app.7290745b9112868a8cd5.hot-update.js",
    "/js/app.df4c72cfe3ef8c469507.hot-update.js": "/js/app.df4c72cfe3ef8c469507.hot-update.js",
    "/js/app.e873e1c59bc80c44fe40.hot-update.js": "/js/app.e873e1c59bc80c44fe40.hot-update.js",
    "/js/app.0b0dce0abee16dc1fb8f.hot-update.js": "/js/app.0b0dce0abee16dc1fb8f.hot-update.js",
    "/js/app.50ef701c83cc842f7a57.hot-update.js": "/js/app.50ef701c83cc842f7a57.hot-update.js",
    "/js/app.7d4dcaf6fe3ebf41bed6.hot-update.js": "/js/app.7d4dcaf6fe3ebf41bed6.hot-update.js",
    "/js/app.774722bc0f8dcf3e54f5.hot-update.js": "/js/app.774722bc0f8dcf3e54f5.hot-update.js",
    "/js/app.45b8463b2a6c01ba3e01.hot-update.js": "/js/app.45b8463b2a6c01ba3e01.hot-update.js",
    "/js/app.b4f637092cc529063861.hot-update.js": "/js/app.b4f637092cc529063861.hot-update.js",
    "/js/app.7540051a565983de7f28.hot-update.js": "/js/app.7540051a565983de7f28.hot-update.js",
    "/js/app.4117f35a7acddd37aad0.hot-update.js": "/js/app.4117f35a7acddd37aad0.hot-update.js"
}
