{
    "list": [
        {
            "id": 1563,
            "firstName": "Антон",
            "lastName": "Пономарёвa",
            "body": "Чичикова, показав во всех отношениях. После ужина Ноздрев сказал.",
            "createdAt": 1586764221,
            "updatedAt": 1586764221,
            "isEdited": false,
            "isRead": 1,
            "isMine": false,
            "userPic": "https://lorempixel.com/640/480/people/",
            "chatId": null
        },
        {
            "id": 1564,
            "firstName": "Людмила",
            "lastName": "Прохоров",
            "body": "Чичиков. — Ну, что человечек, брось его! поедем во мне! каким.",
            "createdAt": 1586764221,
            "updatedAt": 1586764221,
            "isEdited": false,
            "isRead": 1,
            "isMine": false,
            "userPic": "https://lorempixel.com/640/480/people/",
            "chatId": null
        },
        {
            "id": 1565,
            "firstName": "Лаврентий",
            "lastName": "Логиновa",
            "body": "Митяй и дядя Миняй сели оба на коренного, а на пристяжного посадили.",
            "createdAt": 1586764221,
            "updatedAt": 1586764221,
            "isEdited": false,
            "isRead": 0,
            "isMine": false,
            "userPic": "https://lorempixel.com/640/480/people/",
            "chatId": null
        },
        {
            "id": 1566,
            "firstName": "Нестор",
            "lastName": "Вороновa",
            "body": "Фемистоклюс. — Умница, душенька! — сказал — Манилов и повел их к.",
            "createdAt": 1586764221,
            "updatedAt": 1586764221,
            "isEdited": false,
            "isRead": 0,
            "isMine": false,
            "userPic": "https://lorempixel.com/640/480/people/",
            "chatId": null
        },
        {
            "id": 1567,
            "firstName": "Людмила",
            "lastName": "Прохоров",
            "body": "Петрушка ничего не отвечал. — Прощайте, почтеннейший друг! Не.",
            "createdAt": 1586764221,
            "updatedAt": 1586764221,
            "isEdited": false,
            "isRead": 0,
            "isMine": false,
            "userPic": "https://lorempixel.com/640/480/people/",
            "chatId": null
        },
        {
            "id": 1568,
            "firstName": "Кристина",
            "lastName": "Мамонтовa",
            "body": "Черта помещица испугалась необыкновенно. — Ох, не припоминай его.",
            "createdAt": 1586764221,
            "updatedAt": 1586764221,
            "isEdited": false,
            "isRead": 0,
            "isMine": true,
            "userPic": "https://plizi.s3.eu-north-1.amazonaws.com/images/originals/3RLqW9qjU49BjJG4M9fc6uHt1eG064KFJATNG1Tt.png",
            "chatId": null
        },
        {
            "id": 1569,
            "firstName": "Назар",
            "lastName": "Лыткин",
            "body": "России? Здесь Манилов, сделавши некоторое движение головою.",
            "createdAt": 1586764221,
            "updatedAt": 1586764221,
            "isEdited": false,
            "isRead": 0,
            "isMine": false,
            "userPic": "https://lorempixel.com/640/480/people/",
            "chatId": null
        },
        {
            "id": 1570,
            "firstName": "Доминика",
            "lastName": "Куликов",
            "body": "А вот же поймал, нарочно поймал! — отвечал на это ничего не имел у.",
            "createdAt": 1586764221,
            "updatedAt": 1586764221,
            "isEdited": false,
            "isRead": 1,
            "isMine": false,
            "userPic": "https://lorempixel.com/640/480/people/",
            "chatId": null
        },
        {
            "id": 1571,
            "firstName": "Марат",
            "lastName": "Фролов",
            "body": "А вот — вы не хотите продать, прощайте! — Позвольте, я сейчас.",
            "createdAt": 1586764221,
            "updatedAt": 1586764221,
            "isEdited": false,
            "isRead": 1,
            "isMine": false,
            "userPic": "https://lorempixel.com/640/480/people/",
            "chatId": null
        },
        {
            "id": 1572,
            "firstName": "Назар",
            "lastName": "Лыткин",
            "body": "Хотя ему на глаза в лавках: хомутов, курительных свечек, платков для.",
            "createdAt": 1586764221,
            "updatedAt": 1586764221,
            "isEdited": false,
            "isRead": 1,
            "isMine": false,
            "userPic": "https://lorempixel.com/640/480/people/",
            "chatId": null
        },
        {
            "id": 1573,
            "firstName": "Евгений",
            "lastName": "Комаров",
            "body": "Вы как, — матушка? — Бог приберег от такой беды, пожар бы еще отдать.",
            "createdAt": 1586764221,
            "updatedAt": 1586764221,
            "isEdited": false,
            "isRead": 1,
            "isMine": false,
            "userPic": "https://lorempixel.com/640/480/people/",
            "chatId": null
        }
    ]
}
